w1datalogger/__init__.py
w1datalogger/logger.py
w1_datalogger-0.6.0.dist-info/LICENSE
w1_datalogger-0.6.0.dist-info/METADATA
w1_datalogger-0.6.0.dist-info/WHEEL
w1_datalogger-0.6.0.dist-info/entry_points.txt
w1_datalogger-0.6.0.dist-info/top_level.txt
w1_datalogger-0.6.0.dist-info/zip-safe
w1_datalogger-0.6.0.dist-info/RECORD
