Metadata-Version: 2.1
Name: w1-datalogger
Version: 0.6.0
Summary: Log data from local w1 busses to a cloud endpoint
Home-page: UNKNOWN
Author: Steve Work
Author-email: steve@work.renlabs.com
License: UNKNOWN
Platform: UNKNOWN
Classifier: Programming Language :: Python :: 3
Classifier: Operating System :: POSIX :: Linux
Classifier: License :: OSI Approved :: MIT License
Requires-Dist: requests (<3,>=2)
